{
	"name": "eyeBoss",
	"plugin-id": "Sprite",
	"sid": 861341650251964,
	"isGlobal": false,
	"instanceVariables": [],
	"behaviorTypes": [
		{
			"behaviorId": "Platform",
			"name": "Platform",
			"sid": 334603277877867
		},
		{
			"behaviorId": "Turret",
			"name": "Turret",
			"sid": 505816295516779
		},
		{
			"behaviorId": "solid",
			"name": "Solid",
			"sid": 268701210472519
		}
	],
	"effectTypes": [],
	"animations": {
		"items": [
			{
				"frames": [
					{
						"width": 37,
						"height": 46,
						"originX": 0.5,
						"originY": 0.5,
						"originalSource": "",
						"exportFormat": "lossless",
						"exportQuality": 0.8,
						"fileType": "image/png",
						"imageSpriteId": 1988035,
						"collisionPoly": {
							"points": [
								0.4594594594594595,
								0.021739130434782608,
								0.6486486486486487,
								0.021739130434782608,
								0.8108108108108109,
								0.08695652173913043,
								0.8918918918918919,
								0.15217391304347827,
								0.9459459459459459,
								0.2391304347826087,
								0.972972972972973,
								0.30434782608695654,
								0.972972972972973,
								0.43478260869565216,
								0.8918918918918919,
								0.6086956521739131,
								0.5292792792792802,
								0.7499999999999998,
								0.38344594594594733,
								0.714221014492753,
								0.46734234234234284,
								0.8740942028985507,
								0.3783783783783784,
								0.9782608695652174,
								0.2972972972972973,
								0.9782608695652174,
								0.24324324324324326,
								0.9347826086956522,
								0.3108108108108107,
								0.8188405797101455,
								0.07207207207207209,
								0.7192028985507248,
								0.02702702702702703,
								0.6521739130434783,
								0.02702702702702703,
								0.5434782608695652,
								0.13513513513513514,
								0.2391304347826087,
								0.16216216216216217,
								0.1956521739130435,
								0.2972972972972973,
								0.08695652173913043,
								0.3783783783783784,
								0.043478260869565216
							]
						},
						"useCollisionPoly": true,
						"imagePoints": [
							{
								"name": "Image Point 1",
								"x": 0.7567567567567568,
								"y": 0.3695652173913043
							}
						],
						"duration": 18,
						"tag": ""
					},
					{
						"width": 65,
						"height": 50,
						"originX": 0.5,
						"originY": 0.5,
						"originalSource": "",
						"exportFormat": "lossless",
						"exportQuality": 0.8,
						"fileType": "image/png",
						"imageSpriteId": 995708,
						"collisionPoly": {
							"points": [
								0.47692307692307695,
								0.06,
								0.5846153846153846,
								0.06,
								0.676923076923077,
								0.12,
								0.7230769230769231,
								0.18,
								0.7538461538461538,
								0.26,
								0.7692307692307693,
								0.32,
								0.7692307692307693,
								0.44,
								0.7230769230769231,
								0.6,
								0.4307692307692308,
								0.94,
								0.38461538461538464,
								0.94,
								0.35384615384615387,
								0.9,
								0.24615384615384617,
								0.68,
								0.23076923076923078,
								0.64,
								0.23076923076923078,
								0.54,
								0.2923076923076923,
								0.26,
								0.3076923076923077,
								0.22,
								0.38461538461538464,
								0.12,
								0.4307692307692308,
								0.08
							]
						},
						"useCollisionPoly": true,
						"duration": 1,
						"tag": ""
					},
					{
						"width": 65,
						"height": 50,
						"originX": 0.5,
						"originY": 0.5,
						"originalSource": "",
						"exportFormat": "lossless",
						"exportQuality": 0.8,
						"fileType": "image/png",
						"imageSpriteId": 4520672,
						"collisionPoly": {
							"points": [
								0.47692307692307695,
								0.06,
								0.5846153846153846,
								0.06,
								0.676923076923077,
								0.12,
								0.7230769230769231,
								0.18,
								0.7538461538461538,
								0.26,
								0.7692307692307693,
								0.32,
								0.7692307692307693,
								0.44,
								0.7230769230769231,
								0.6,
								0.4307692307692308,
								0.94,
								0.38461538461538464,
								0.94,
								0.35384615384615387,
								0.9,
								0.24615384615384617,
								0.68,
								0.23076923076923078,
								0.64,
								0.23076923076923078,
								0.54,
								0.2923076923076923,
								0.26,
								0.3076923076923077,
								0.22,
								0.38461538461538464,
								0.12,
								0.4307692307692308,
								0.08
							]
						},
						"useCollisionPoly": true,
						"duration": 1,
						"tag": ""
					},
					{
						"width": 65,
						"height": 50,
						"originX": 0.5,
						"originY": 0.5,
						"originalSource": "",
						"exportFormat": "lossless",
						"exportQuality": 0.8,
						"fileType": "image/png",
						"imageSpriteId": 4851608,
						"collisionPoly": {
							"points": [
								0.47692307692307695,
								0.06,
								0.5846153846153846,
								0.06,
								0.676923076923077,
								0.12,
								0.7230769230769231,
								0.18,
								0.7538461538461538,
								0.26,
								0.7692307692307693,
								0.32,
								0.7692307692307693,
								0.44,
								0.7230769230769231,
								0.6,
								0.4307692307692308,
								0.94,
								0.38461538461538464,
								0.94,
								0.35384615384615387,
								0.9,
								0.24615384615384617,
								0.68,
								0.23076923076923078,
								0.64,
								0.23076923076923078,
								0.54,
								0.2923076923076923,
								0.26,
								0.3076923076923077,
								0.22,
								0.38461538461538464,
								0.12,
								0.4307692307692308,
								0.08
							]
						},
						"useCollisionPoly": true,
						"duration": 1,
						"tag": ""
					},
					{
						"width": 65,
						"height": 50,
						"originX": 0.5,
						"originY": 0.5,
						"originalSource": "",
						"exportFormat": "lossless",
						"exportQuality": 0.8,
						"fileType": "image/png",
						"imageSpriteId": 3738661,
						"collisionPoly": {
							"points": [
								0.47692307692307695,
								0.06,
								0.5846153846153846,
								0.06,
								0.676923076923077,
								0.12,
								0.7230769230769231,
								0.18,
								0.7538461538461538,
								0.26,
								0.7692307692307693,
								0.32,
								0.7692307692307693,
								0.44,
								0.7230769230769231,
								0.6,
								0.4307692307692308,
								0.94,
								0.38461538461538464,
								0.94,
								0.35384615384615387,
								0.9,
								0.24615384615384617,
								0.68,
								0.23076923076923078,
								0.64,
								0.23076923076923078,
								0.54,
								0.2923076923076923,
								0.26,
								0.3076923076923077,
								0.22,
								0.38461538461538464,
								0.12,
								0.4307692307692308,
								0.08
							]
						},
						"useCollisionPoly": true,
						"duration": 1,
						"tag": ""
					},
					{
						"width": 65,
						"height": 50,
						"originX": 0.5,
						"originY": 0.5,
						"originalSource": "",
						"exportFormat": "lossless",
						"exportQuality": 0.8,
						"fileType": "image/png",
						"imageSpriteId": 3475275,
						"collisionPoly": {
							"points": [
								0.47692307692307695,
								0.06,
								0.5846153846153846,
								0.06,
								0.676923076923077,
								0.12,
								0.7230769230769231,
								0.18,
								0.7538461538461538,
								0.26,
								0.7692307692307693,
								0.32,
								0.7692307692307693,
								0.44,
								0.7230769230769231,
								0.6,
								0.4307692307692308,
								0.94,
								0.38461538461538464,
								0.94,
								0.35384615384615387,
								0.9,
								0.24615384615384617,
								0.68,
								0.23076923076923078,
								0.64,
								0.23076923076923078,
								0.54,
								0.2923076923076923,
								0.26,
								0.3076923076923077,
								0.22,
								0.38461538461538464,
								0.12,
								0.4307692307692308,
								0.08
							]
						},
						"useCollisionPoly": true,
						"duration": 1,
						"tag": ""
					}
				],
				"sid": 281060655260364,
				"name": "Animation 1",
				"isLooping": true,
				"isPingPong": true,
				"repeatCount": 1,
				"repeatTo": 0,
				"speed": 5
			},
			{
				"frames": [
					{
						"width": 37,
						"height": 46,
						"originX": 0.5,
						"originY": 0.5,
						"originalSource": "",
						"exportFormat": "lossless",
						"exportQuality": 0.8,
						"fileType": "image/png",
						"imageSpriteId": 987363,
						"collisionPoly": {
							"points": [
								0.4594594594594595,
								0.021739130434782608,
								0.6486486486486487,
								0.021739130434782608,
								0.8108108108108109,
								0.08695652173913043,
								0.8918918918918919,
								0.15217391304347827,
								0.9459459459459459,
								0.2391304347826087,
								0.972972972972973,
								0.30434782608695654,
								0.972972972972973,
								0.43478260869565216,
								0.8918918918918919,
								0.6086956521739131,
								0.3783783783783784,
								0.9782608695652174,
								0.2972972972972973,
								0.9782608695652174,
								0.24324324324324326,
								0.9347826086956522,
								0.05405405405405406,
								0.6956521739130435,
								0.02702702702702703,
								0.6521739130434783,
								0.02702702702702703,
								0.5434782608695652,
								0.13513513513513514,
								0.2391304347826087,
								0.16216216216216217,
								0.1956521739130435,
								0.2972972972972973,
								0.08695652173913043,
								0.3783783783783784,
								0.043478260869565216
							]
						},
						"useCollisionPoly": true,
						"duration": 1,
						"tag": ""
					},
					{
						"width": 65,
						"height": 50,
						"originX": 0.5,
						"originY": 0.5,
						"originalSource": "",
						"exportFormat": "lossless",
						"exportQuality": 0.8,
						"fileType": "image/png",
						"imageSpriteId": 5914861,
						"collisionPoly": {
							"points": [
								0.47692307692307695,
								0.06,
								0.5230769230769231,
								0.06,
								0.5538461538461539,
								0.7,
								0.47692307692307695,
								0.88,
								0.4307692307692308,
								0.94,
								0.38461538461538464,
								0.94,
								0.35384615384615387,
								0.9,
								0.24615384615384617,
								0.68,
								0.23076923076923078,
								0.64,
								0.23076923076923078,
								0.54,
								0.2923076923076923,
								0.26,
								0.3076923076923077,
								0.22,
								0.38461538461538464,
								0.12,
								0.4307692307692308,
								0.08
							]
						},
						"useCollisionPoly": true,
						"duration": 1,
						"tag": ""
					},
					{
						"width": 65,
						"height": 50,
						"originX": 0.5,
						"originY": 0.5,
						"originalSource": "",
						"exportFormat": "lossless",
						"exportQuality": 0.8,
						"fileType": "image/png",
						"imageSpriteId": 7973164,
						"collisionPoly": {
							"points": [
								0.4461538461538462,
								0.08,
								0.5076923076923077,
								0.7,
								0.47692307692307695,
								0.88,
								0.4307692307692308,
								0.94,
								0.38461538461538464,
								0.94,
								0.35384615384615387,
								0.9,
								0.24615384615384617,
								0.68,
								0.23076923076923078,
								0.64,
								0.23076923076923078,
								0.54,
								0.2923076923076923,
								0.26,
								0.3076923076923077,
								0.22,
								0.38461538461538464,
								0.12
							]
						},
						"useCollisionPoly": true,
						"duration": 1,
						"tag": ""
					},
					{
						"width": 65,
						"height": 50,
						"originX": 0.5,
						"originY": 0.5,
						"originalSource": "",
						"exportFormat": "lossless",
						"exportQuality": 0.8,
						"fileType": "image/png",
						"imageSpriteId": 2166174,
						"collisionPoly": {
							"points": [
								0.3076923076923077,
								0.44,
								0.47692307692307695,
								0.78,
								0.47692307692307695,
								0.88,
								0.4307692307692308,
								0.94,
								0.38461538461538464,
								0.94,
								0.35384615384615387,
								0.9,
								0.24615384615384617,
								0.68,
								0.23076923076923078,
								0.64,
								0.23076923076923078,
								0.54
							]
						},
						"useCollisionPoly": true,
						"duration": 1,
						"tag": ""
					},
					{
						"width": 65,
						"height": 50,
						"originX": 0.5,
						"originY": 0.5,
						"originalSource": "",
						"exportFormat": "lossless",
						"exportQuality": 0.8,
						"fileType": "image/png",
						"imageSpriteId": 6942532,
						"collisionPoly": {
							"points": [
								0.23076923076923078,
								0.62,
								0.3076923076923077,
								0.62,
								0.4307692307692308,
								0.7,
								0.47692307692307695,
								0.78,
								0.47692307692307695,
								0.88,
								0.4307692307692308,
								0.94,
								0.38461538461538464,
								0.94,
								0.35384615384615387,
								0.9,
								0.24615384615384617,
								0.68
							]
						},
						"useCollisionPoly": true,
						"duration": 1,
						"tag": ""
					},
					{
						"width": 65,
						"height": 50,
						"originX": 0.5,
						"originY": 0.5,
						"originalSource": "",
						"exportFormat": "lossless",
						"exportQuality": 0.8,
						"fileType": "image/png",
						"imageSpriteId": 3441072,
						"collisionPoly": {
							"points": [
								0.4153846153846154,
								0.76,
								0.47692307692307695,
								0.78,
								0.47692307692307695,
								0.88,
								0.4307692307692308,
								0.94,
								0.38461538461538464,
								0.94,
								0.35384615384615387,
								0.9,
								0.35384615384615387,
								0.86
							]
						},
						"useCollisionPoly": true,
						"duration": 1,
						"tag": ""
					}
				],
				"sid": 236971091916885,
				"name": "Animation 2",
				"isLooping": false,
				"isPingPong": false,
				"repeatCount": 1,
				"repeatTo": 0,
				"speed": 5
			}
		],
		"subfolders": []
	}
}